[{"active":true,
  "visible":true,
  "collideBottom":true,
  "collideLeft":true,
  "collideRight":true,
  "collideTop":true,
  "on":true,
  "particleBringToTop":true,
  "radial":true,
  "frame":{"frames":["symbol_02"],
    "cycle":false,
    "quantity":1},
  "frequency":0,
  "gravityX":0,
  "gravityY":0,
  "maxParticles":0,
  "timeScale":0.5,
  "blendMode":3,
  "accelerationX":0,
  "accelerationY":0,
  "alpha":1,
  "angle":{"min":0,
    "max":360,
    "ease":"Linear"},
  "bounce":{"ease":"Linear",
    "min":1,
    "max":500},
  "delay":{"ease":"Linear",
    "min":1,
    "max":500},
  "lifespan":{"ease":"Linear",
    "min":1,
    "max":50000},
  "maxVelocityX":{"start":0,
    "end":0,
    "ease":"Linear"},
  "maxVelocityY":10000,
  "moveToX":0,
  "moveToY":0,
  "quantity":1,
  "rotate":0,
  "scale":{"ease":"Linear",
    "min":1,
    "max":2},
  "speed":{"ease":"Linear",
    "min":1,
    "max":500},
  "x":{"ease":"Linear",
    "min":0,
    "max":1000},
  "y":{"ease":"Linear",
    "min":1,
    "max":1000},
  "tint":[11142573,
    7441958,
    3893608,
    12013648],
  "emitZone":{"source":new Phaser.Geom.Circle(0,0,50),"type":"random"}}]
